setup.py
src/wellcome_lambda_utils/__init__.py
src/wellcome_lambda_utils/deployment_utils.py
src/wellcome_lambda_utils/dynamo_utils.py
src/wellcome_lambda_utils/ecs_utils.py
src/wellcome_lambda_utils/miro_utils.py
src/wellcome_lambda_utils/s3_utils.py
src/wellcome_lambda_utils/sns_utils.py
src/wellcome_lambda_utils.egg-info/PKG-INFO
src/wellcome_lambda_utils.egg-info/SOURCES.txt
src/wellcome_lambda_utils.egg-info/dependency_links.txt
src/wellcome_lambda_utils.egg-info/requires.txt
src/wellcome_lambda_utils.egg-info/top_level.txt