Metadata-Version: 1.2
Name: wellcome-lambda-utils
Version: 2017.10.27
Summary: Common lib for lambdas
Home-page: https://github.com/wellcometrust/platform
Author: Wellcome digital platform
Author-email: wellcomedigitalplatform@wellcome.ac.uk
License: UNKNOWN
Keywords: lambda,utils
Platform: UNKNOWN
Requires-Python: >=3.6
